cuda/core/__init__.py
cuda/core/_version.py
cuda/core/_include/dlpack.h
cuda/core/_include/layout.hpp
cuda/core/_include/utility.hpp
cuda/core/cu12/__init__.pxd
cuda/core/cu12/__init__.py
cuda/core/cu12/_context.cp314-win_amd64.pyd
cuda/core/cu12/_context.cpp
cuda/core/cu12/_context.pyx
cuda/core/cu12/_device.cp314-win_amd64.pyd
cuda/core/cu12/_device.cpp
cuda/core/cu12/_device.pyx
cuda/core/cu12/_dlpack.cp314-win_amd64.pyd
cuda/core/cu12/_dlpack.cpp
cuda/core/cu12/_dlpack.pxd
cuda/core/cu12/_dlpack.pyx
cuda/core/cu12/_event.cp314-win_amd64.pyd
cuda/core/cu12/_event.cpp
cuda/core/cu12/_event.pxd
cuda/core/cu12/_event.pyx
cuda/core/cu12/_graph.py
cuda/core/cu12/_kernel_arg_handler.cp314-win_amd64.pyd
cuda/core/cu12/_kernel_arg_handler.cpp
cuda/core/cu12/_kernel_arg_handler.pxd
cuda/core/cu12/_kernel_arg_handler.pyx
cuda/core/cu12/_launch_config.cp314-win_amd64.pyd
cuda/core/cu12/_launch_config.cpp
cuda/core/cu12/_launch_config.pxd
cuda/core/cu12/_launch_config.pyx
cuda/core/cu12/_launcher.cp314-win_amd64.pyd
cuda/core/cu12/_launcher.cpp
cuda/core/cu12/_launcher.pyx
cuda/core/cu12/_layout.cp314-win_amd64.pyd
cuda/core/cu12/_layout.cpp
cuda/core/cu12/_layout.pxd
cuda/core/cu12/_layout.pyx
cuda/core/cu12/_linker.py
cuda/core/cu12/_memoryview.cp314-win_amd64.pyd
cuda/core/cu12/_memoryview.cpp
cuda/core/cu12/_memoryview.pyx
cuda/core/cu12/_module.py
cuda/core/cu12/_program.py
cuda/core/cu12/_stream.cp314-win_amd64.pyd
cuda/core/cu12/_stream.cpp
cuda/core/cu12/_stream.pxd
cuda/core/cu12/_stream.pyx
cuda/core/cu12/_system.py
cuda/core/cu12/_version.py
cuda/core/cu12/utils.py
cuda/core/cu12/_include/dlpack.h
cuda/core/cu12/_include/layout.hpp
cuda/core/cu12/_include/utility.hpp
cuda/core/cu12/_memory/__init__.pxd
cuda/core/cu12/_memory/__init__.py
cuda/core/cu12/_memory/_buffer.cp314-win_amd64.pyd
cuda/core/cu12/_memory/_buffer.cpp
cuda/core/cu12/_memory/_buffer.pxd
cuda/core/cu12/_memory/_buffer.pyx
cuda/core/cu12/_memory/_device_memory_resource.cp314-win_amd64.pyd
cuda_core-0.5.1.dist-info/licenses/LICENSE
cuda_core-0.5.1.dist-info/DELVEWHEEL
cuda_core-0.5.1.dist-info/METADATA
cuda_core-0.5.1.dist-info/WHEEL
cuda_core-0.5.1.dist-info/top_level.txt
cuda_core-0.5.1.dist-info/RECORD
