Metadata-Version: 2.4
Name: cuda-core
Version: 0.5.1
Summary: cuda.core: (experimental) pythonic CUDA module
Author: NVIDIA Corporation
License-Expression: Apache-2.0
Project-URL: homepage, https://nvidia.github.io/cuda-python/
Project-URL: documentation, https://nvidia.github.io/cuda-python/cuda-core/
Project-URL: repository, https://github.com/NVIDIA/cuda-python/tree/main/cuda_core
Project-URL: issues, https://github.com/NVIDIA/cuda-python/issues/
Classifier: Development Status :: 4 - Beta
Classifier: Intended Audience :: Developers
Classifier: Intended Audience :: Science/Research
Classifier: Intended Audience :: End Users/Desktop
Classifier: Natural Language :: English
Classifier: Operating System :: POSIX :: Linux
Classifier: Operating System :: Microsoft :: Windows
Classifier: Topic :: Education
Classifier: Topic :: Scientific/Engineering
Classifier: Topic :: Software Development :: Libraries
Classifier: Programming Language :: Python :: 3 :: Only
Classifier: Programming Language :: Python :: 3.10
Classifier: Programming Language :: Python :: 3.11
Classifier: Programming Language :: Python :: 3.12
Classifier: Programming Language :: Python :: 3.13
Classifier: Programming Language :: Python :: 3.14
Classifier: Programming Language :: Python :: Implementation :: CPython
Classifier: Environment :: GPU :: NVIDIA CUDA
Classifier: Environment :: GPU :: NVIDIA CUDA :: 12
Classifier: Environment :: GPU :: NVIDIA CUDA :: 13
Requires-Python: >=3.10
License-File: LICENSE
Requires-Dist: numpy
Provides-Extra: cu12
Requires-Dist: cuda-bindings[all]==12.*; extra == "cu12"
Provides-Extra: cu13
Requires-Dist: cuda-bindings[all]==13.*; extra == "cu13"
Dynamic: license-file
